LICENSE
MANIFEST.in
README.rst
setup.py
anafero/__init__.py
anafero/admin.py
anafero/callbacks.py
anafero/conf.py
anafero/middleware.py
anafero/models.py
anafero/signals.py
anafero/urls.py
anafero/utils.py
anafero/views.py
anafero.egg-info/PKG-INFO
anafero.egg-info/SOURCES.txt
anafero.egg-info/dependency_links.txt
anafero.egg-info/not-zip-safe
anafero.egg-info/requires.txt
anafero.egg-info/top_level.txt
anafero/templates/anafero/_create_referral_form.html
anafero/templatetags/__init__.py
anafero/templatetags/anafero_tags.py
anafero/tests/__init__.py
anafero/tests/models.py
anafero/tests/tests.py
anafero/tests/urls.py